LICENSE
README.rst
setup.cfg
setup.py
matchingtools/__init__.py
matchingtools/core.py
matchingtools/integration.py
matchingtools/lsttools.py
matchingtools/output.py
matchingtools/permutations.py
matchingtools/transformations.py
matchingtools.egg-info/PKG-INFO
matchingtools.egg-info/SOURCES.txt
matchingtools.egg-info/dependency_links.txt
matchingtools.egg-info/top_level.txt
matchingtools/extras/Lorentz.py
matchingtools/extras/SM.py
matchingtools/extras/SM_dim_6_basis.py
matchingtools/extras/SU2.py
matchingtools/extras/SU3.py
matchingtools/extras/__init__.py