Metadata-Version: 2.1
Name: matchingtools
Version: 0.4.1
Summary: A library for symbolic Effective Field Theory calculations
Home-page: https://github.com/jccriado/matchingtools
Author: Juan Carlos Criado Alamo
Author-email: jccriadoalamo@ugr.es
License: MIT
Keywords: effective field theory symbolic tree matching integration
Platform: UNKNOWN
Classifier: Intended Audience :: Science/Research
Classifier: License :: OSI Approved :: MIT License
Classifier: Operating System :: OS Independent
Classifier: Programming Language :: Python
Classifier: Programming Language :: Python :: 2
Classifier: Programming Language :: Python :: 3
Classifier: Topic :: Scientific/Engineering :: Physics
License-File: LICENSE
